[
{
    "id": "1",
    "name": "골드맥앤치즈 비프버거",
    "price": 5600
}
{
    "id": "2",
    "name": "그릴드더블 비프버거",
    "price": 5800
}
{
    "id": "3",
    "name": "불 싸이버거",
    "price": 5200
}
{
    "id": "4",
    "name": "싸이버거",
    "price": 5000
}
{
    "id": "5",
    "name": "디럭스 불고기버거",
    "price": 4800
}
{
    "id": "6",
    "name": "딥치즈 버거",
    "price": 5900
}
{
    "id": "7",
    "name": "인크레더블 버거",
    "price": 5300
}
{
    "id": "8",
    "name": "딥치즈 싸이버거",
    "price": 5900
}
{
    "id": "9",
    "name": "쉬림프 싸이플렉스버거",
    "price": 5600
}
{
    "id": "10",
    "name": "칠리새우버거",
    "price": 5600
}
{
    "id": "11",
    "name": "청양마요 미트볼버거",
    "price": 5800
}
{
    "id": "12",
    "name": "불불불불 싸이버거",
    "price": 5500
}
{
    "id": "13",
    "name": "언빌리버블 버거",
    "price": 5700
}
{
    "id": "14",
    "name": "텍사스바베큐 치킨버거",
    "price": 5600
}
{
    "id": "15",
    "name": "트리플딥치즈비프버거",
    "price": 5600
}
{
    "id": "16",
    "name": "화이트갈릭버거",
    "price": 5100
}
{
    "id": "17",
    "name": "할라피뇨통살버거",
    "price": 5200
}
{
    "id": "18",
    "name": "휠렛버거",
    "price": 5900
}
{
    "id": "19",
    "name": "불고기버거",
    "price": 4800
}
{
    "id": "20",
    "name": "오리지널미트볼버거",
    "price": 5900
}
{
    "id": "21",
    "name": "통새우버거",
    "price": 5900
}
{
    "id": "22",
    "name":"아라비아따치즈버거",
    "price": 5900
}
{
    "id": "23",
    "name": "비프스테이크 버거",
    "price": 5900
}
{
    "id": "24",
    "name": "골드맥앤치즈 치킨버거",
    "price": 5400
}

]